LICENSE
MANIFEST.in
README.rst
setup.py
scripts/tw
twcli/__init__.py
twcli/config.py
twcli/constants.py
twcli/output.py
twcli.egg-info/PKG-INFO
twcli.egg-info/SOURCES.txt
twcli.egg-info/dependency_links.txt
twcli.egg-info/not-zip-safe
twcli.egg-info/top_level.txt