Metadata-Version: 1.1
Name: twcli
Version: 2.0
Summary: TaskWorkshop CLI
Home-page: https://github.com/taskworkshop/taskworkshop-cli
Author: Altermind
Author-email: contact@altermind.pl
License:                     GNU GENERAL PUBLIC LICENSE
